moepy/__init__.py
moepy/_nbdev.py
moepy/cicd.py
moepy/eda.py
moepy/lowess.py
moepy/moe.py
moepy/retrieval.py
moepy/surface.py
moepy-1.1.4.dist-info/LICENSE.txt
moepy-1.1.4.dist-info/METADATA
moepy-1.1.4.dist-info/WHEEL
moepy-1.1.4.dist-info/top_level.txt
moepy-1.1.4.dist-info/RECORD
