Metadata-Version: 2.1
Name: moepy
Version: 1.1.4
Summary: Code and analysis used for calculating the merit order effect of renewables on price and carbon intensity of electricity markets
Home-page: https://AyrtonB.github.io/Merit-Order-Effect/
Author: Ayrton Bourn
Author-email: ayrtonbourn@outlook.com
License: UNKNOWN
Platform: UNKNOWN
Classifier: Programming Language :: Python :: 3
Requires-Python: >=3.6
Requires-Dist: pandas (>=1.2.0)
Requires-Dist: numpy (>=1.19.5)
Requires-Dist: matplotlib (>=3.3.3)
Requires-Dist: tqdm (>=4.59.0)
Requires-Dist: scikit-learn (>=0.24.0)
Requires-Dist: scipy (>=1.6.0)
Provides-Extra: cicd
Requires-Dist: configparser (>=5.0.0) ; extra == 'cicd'
Requires-Dist: typer (>=0.3.2) ; extra == 'cicd'
Provides-Extra: research
Requires-Dist: lxml (>=4.6.2) ; extra == 'research'
Requires-Dist: xmltodict (>=0.12.0) ; extra == 'research'
Requires-Dist: entsoe-py (>=0.3.2) ; extra == 'research'
Requires-Dist: python-dotenv (>=0.15.0) ; extra == 'research'
